kubebox/__init__.py
kubebox/_client.py
kubebox/_manager.py
kubebox/security/__init__.py
kubebox/security/_security.py
kubebox-0.0.15.dist-info/METADATA
kubebox-0.0.15.dist-info/WHEEL
kubebox-0.0.15.dist-info/RECORD
